gogstools-0.1.2.data/scripts/gff2embl
gogstools-0.1.2.data/scripts/ogs_check
gogstools-0.1.2.data/scripts/ogs_merge
ogswriters/BipaaEmblSubmitWriter.py
ogswriters/BipaaEmblWriter.py
ogswriters/__init__.py
gogstools-0.1.2.dist-info/LICENSE
gogstools-0.1.2.dist-info/METADATA
gogstools-0.1.2.dist-info/WHEEL
gogstools-0.1.2.dist-info/top_level.txt
gogstools-0.1.2.dist-info/RECORD
